{
  "autowindow": 80,
  "backbottom": 800,
  "backtop": 800,
  "blob_filter": 1,
  "blob_maxsize": 10000,
  "blob_minsize": 65,
  "blob_param1": 100,
  "bottom": 479,
  "confidence": 200,
  "debug": 0,
  "front": 0,
  "left": 0,
  "right": 639,
  "showfps": 0,
  "showmask": 0,
  "showrawdepth": 0,
  "showregionhits": 1,
  "showregionmap": 0,
  "showregionrects": 0,
  "tilt": 0,
  "top": 0,
  "usemask": 1,
  "regions": [
    { "first_sid": 11000, "x": 107, "y": 139, "width": 113, "height": 62},
    { "first_sid": 12000, "x": 171, "y": 82, "width": 138, "height": 50},
    { "first_sid": 13000, "x": 23, "y": 83, "width": 134, "height": 49},
    { "first_sid": 14000, "x": 108, "y": 10, "width": 112, "height": 62},
    { "first_sid": 21000, "x": 227, "y": 167, "width": 28, "height": 17},
    { "first_sid": 22000, "x": 266, "y": 140, "width": 25, "height": 17},
    { "first_sid": 23000, "x": 227, "y": 140, "width": 30, "height": 18},
    { "first_sid": 31000, "x": 74, "y": 165, "width": 25, "height": 17},
    { "first_sid": 32000, "x": 72, "y": 139, "width": 27, "height": 18},
    { "first_sid": 33000, "x": 40, "y": 140, "width": 24, "height": 16},
    { "first_sid": 41000, "x": 268, "y": 56, "width": 25, "height": 18},
    { "first_sid": 42000, "x": 230, "y": 56, "width": 27, "height": 16},
    { "first_sid": 43000, "x": 230, "y": 29, "width": 27, "height": 16},
    { "first_sid": 51000, "x": 73, "y": 57, "width": 26, "height": 16},
    { "first_sid": 52000, "x": 38, "y": 58, "width": 25, "height": 16},
    { "first_sid": 53000, "x": 72, "y": 30, "width": 26, "height": 17}
  ]

}
