{
    "params":{
        "alphafinal":"0.000",
        "alphainitial":"0.850",
        "alphatime":"7.304",
        "aspect":"0.500",
        "bounce":"false",
        "filled":"false",
        "gravity":"0",
        "hue1final":"360.000",
        "hue1initial":"36.000",
        "hue1time":"1.004",
        "hue2final":"360.000",
        "hue2initial":"36.000",
        "hue2time":"1.004",
        "justification":"center",
        "lifetime":"10.000",
        "luminance":"0.500",
        "mirrortype":"none",
        "movedir":"cursor",
        "noisevertexx":"0.000",
        "noisevertexy":"0.000",
        "nsprites":"47",
        "placement":"cursor",
        "rotangdir":"left",
        "rotanginit":"90.000",
        "rotangspeed":"72.000",
        "rotauto":"true",
        "saturation":"1.000",
        "shape":"circle",
        "sizefinal":"10.000",
        "sizeinitial":"2.999",
        "sizetime":"1.054",
        "smoothxyz":"3",
        "speed":"0.130",
        "spritesource":"cursor",
        "thickness":"1.471",
        "zmin":"0.004"
    }
}
