{
    "params":{
        "alphafinal":"0.000",
        "alphainitial":"0.700",
        "alphatime":"1.290",
        "aspect":"1.000",
        "bounce":"false",
        "cursorsprites":"true",
        "filled":"false",
        "hue1final":"288.000",
        "hue1initial":"180.360",
        "hue1time":"2.003",
        "hue2final":"288.000",
        "hue2initial":"180.360",
        "hue2time":"2.003",
        "lifetime":"10.000",
        "luminance":"0.500",
        "mirrortype":"none",
        "movedir":"left",
        "noisevertex":"0.000",
        "nsprites":"147",
        "rotangdir":"right",
        "rotanginit":"45.000",
        "rotangspeed":"72.000",
        "rotauto":"false",
        "saturation":"1.000",
        "shape":"square",
        "sizefinal":"6.000",
        "sizeinitial":"9.992",
        "sizetime":"0.281",
        "smoothxyz":"3",
        "speed":"0.000",
        "thickness":"9.253"
    }
}
