{"location":"IdeaFabLabs","hostname":"spacepalette34","color":"#2ca02c"}
{"location":"MADE","hostname":"spacepalette35","color":"#d62728"}
{"location":"CatFactory","hostname":"spacepalette36","color":"#ff7f0e"}
{"location":"CarletonUniversity","hostname":"palette12","color":"#1f77b4"}
{"location":"TIAT-Montera","hostname":"spacepalette37","color":"#9467bd"}
{"location":"KALEID","hostname":"palette7","color":"#8c564b"}
{"location":"PrairieWillow","hostname":"spacepalette33","color":"#e377c2"}
{"location":"GeorgeMark","hostname":"spacepalette38","color":"#7f7f7f"}
